{"result":{"input":{"address":{"state":"IL","street":"15630 Marshfield","city":"Harvey"},"benchmark":{"id":"9","isDefault":false,"benchmarkName":"Public_AR_Census2010","benchmarkDescription":"Public Address Ranges - Census 2010 Benchmark"},"vintage":{"id":"910","vintageName":"Census2010_Census2010","isDefault":true,"vintageDescription":"Census2010 Vintage - Census2010 Benchmark"}},"addressMatches":[{"geographies":{"Census Blocks":[{"BLKGRP":"2","UR":"","OID":210404038747459,"FUNCSTAT":"S","STATE":"17","AREAWATER":0,"NAME":"Block 2002","SUFFIX":"","LSADC":"BK","CENTLON":"-087.6574633","HU100":13,"LWBLKTYP":"L","BLOCK":"2002","BASENAME":"2002","INTPTLAT":"+41.6053712","POP100":39,"MTFCC":"G5040","COUNTY":"031","GEOID":"170318274002002","CENTLAT":"+41.6053712","INTPTLON":"-087.6574633","AREALAND":10143,"OBJECTID":2806101,"TRACT":"827400"}]},"matchedAddress":"15630 Marshfield Ave, HARVEY, IL, 60426","coordinates":{"x":-87.65718,"y":41.60569},"tigerLine":{"side":"R","tigerLineId":"111705715"},"addressComponents":{"fromAddress":"15600","toAddress":"15698","preQualifier":"","preDirection":"","preType":"","streetName":"Marshfield","suffixType":"Ave","suffixDirection":"","suffixQualifier":"","state":"IL","zip":"60426","city":"HARVEY"}}]}}